{
    "alternateMasterTitleIds": [], 
    "brand": null, 
    "bundleOffers": [], 
    "contentId": null, 
    "countries": {
        "bannedCountries": [], 
        "catalogPrice": null, 
        "catalogPriceA": [], 
        "countryCurrency": null, 
        "countryCurrencyA": [], 
        "giftable": null, 
        "hasSubscriberDiscount": null, 
        "hideStoreChannels": [], 
        "inStock": null, 
        "isPublished": false, 
        "isPurchasable": null
    }, 
    "developerFacetKey": null, 
    "duration": null, 
    "durationUnit": null, 
    "dynamicPricing": "N", 
    "extraContent": [], 
    "extraContentDisplayGroup": null, 
    "extraContentDisplayGroupSortAsc": null, 
    "franchiseFacetKey": "battlefield", 
    "gameDistributionSubType": "Normal Game", 
    "gameEditionTypeFacetKey": "Standard Edition", 
    "gameEditionTypeFacetKeyRankDesc": "3000", 
    "gameNameFacetKey": "battlefield-4", 
    "gameRatingDesc": [], 
    "gameRatingDescriptionLong": null, 
    "gameRatingPendingMature": null, 
    "gameRatingReason": null, 
    "gameRatingType": null, 
    "gameRatingTypeValue": null, 
    "gameRatingUrl": null, 
    "gameTypeFacetKey": "BASEGAME", 
    "genreFacetKey": null, 
    "i18n": {
        "brand": null, 
        "developerFacetKey": null, 
        "displayName": "Frostbite Progressive Installation Test", 
        "eulaURL": null, 
        "extraContentDisplayGroupDisplayName": null, 
        "franchiseFacetKey": null, 
        "franchisePageLink": null, 
        "gameForumURL": null, 
        "gameManualURL": null, 
        "gameTypeFacetKey": null, 
        "genreFacetKey": null, 
        "longDescription": null, 
        "mediumDescription": null, 
        "numberOfPlayersFacetKey": null, 
        "officialSiteURL": null, 
        "onlineDisclaimer": null, 
        "packArtLarge": null, 
        "packArtMedium": null, 
        "packArtSmall": null, 
        "platformFacetKey": null, 
        "preAnnouncementDisplayDate": null, 
        "publisherFacetKey": null, 
        "ratingSystemIcon": null, 
        "shortDescription": null, 
        "systemRequirements": null
    }, 
    "imageServer": "https://Eaassets-a.akamaihd.net/origin-com-store-final-assets-prod", 
    "includeOffers": [], 
    "isDownloadable": "True", 
    "isShellBundle": "N", 
    "isThirdPartyTitle": null, 
    "itemId": "Origin.ITM.50.0000991", 
    "itemName": "Frostbite Progressive Installation Test Item", 
    "itemType": "Base Game", 
    "masterTitle": "ORIGIN SAMPLE INSTALLER", 
    "masterTitleId": "194656", 
    "mdmItemType": "Full Game", 
    "numberOfPlayersFacetKey": null, 
    "offerId": "Origin.OFR.50.0001031", 
    "offerPath": "/battlefield/battlefield-4/standard-edition", 
    "offerType": "Base Game", 
    "originDisplayType": "Full Game", 
    "platformFacetKey": null, 
    "platforms": [
        {
            "achievementSetOverride": null, 
            "commerceProfile": null, 
            "downloadPackageType": null, 
            "downloadStartDate": "2015-05-04T07:00:00Z", 
            "executePathOverride": null, 
            "multiPlayerId": null, 
            "originSubscriptionUseEndDate": null, 
            "platform": "PCWIN", 
            "releaseDate": "2015-05-04T07:00:00Z", 
            "showSubsSaveGameWarning": null, 
            "useEndDate": null
        }
    ], 
    "projectNumber": "313432", 
    "publisherFacetKey": null, 
    "ratingSystemIcon": null, 
    "rbuCode": "3131", 
    "revenueModel": "Digital - Full Game", 
    "softwareLocales": [], 
    "storeGroupId": "Origin", 
    "suppressedOfferIds": [], 
    "trialLaunchDuration": null, 
    "vault": null
}