{
    "baseAttributes": {
        "platform": "PCWIN"
    }, 
    "countries": {
        "country": [
            {
                "attributes": {
                    "isPurchasable": true
                }, 
                "countryCode": "AO"
            }, 
            {
                "attributes": {
                    "isPurchasable": true
                }, 
                "countryCode": "AQ"
            }, 
            {
                "attributes": {
                    "isPurchasable": true
                }, 
                "countryCode": "AS"
            }, 
            {
                "attributes": {
                    "isPurchasable": true
                }, 
                "countryCode": "AU"
            }, 
            {
                "attributes": {
                    "isPurchasable": true
                }, 
                "countryCode": "BF"
            }, 
            {
                "attributes": {
                    "isPurchasable": true
                }, 
                "countryCode": "BI"
            }, 
            {
                "attributes": {
                    "isPurchasable": true
                }, 
                "countryCode": "BJ"
            }, 
            {
                "attributes": {
                    "isPurchasable": true
                }, 
                "countryCode": "BW"
            }, 
            {
                "attributes": {
                    "isPurchasable": true
                }, 
                "countryCode": "CD"
            }, 
            {
                "attributes": {
                    "isPurchasable": true
                }, 
                "countryCode": "CF"
            }, 
            {
                "attributes": {
                    "isPurchasable": true
                }, 
                "countryCode": "CG"
            }, 
            {
                "attributes": {
                    "isPurchasable": true
                }, 
                "countryCode": "CI"
            }, 
            {
                "attributes": {
                    "isPurchasable": true
                }, 
                "countryCode": "CK"
            }, 
            {
                "attributes": {
                    "isPurchasable": true
                }, 
                "countryCode": "CM"
            }, 
            {
                "attributes": {
                    "isPurchasable": true
                }, 
                "countryCode": "CV"
            }, 
            {
                "attributes": {
                    "isPurchasable": true
                }, 
                "countryCode": "CX"
            }, 
            {
                "attributes": {
                    "isPurchasable": true
                }, 
                "countryCode": "DEFAULT"
            }, 
            {
                "attributes": {
                    "isPurchasable": true
                }, 
                "countryCode": "DJ"
            }, 
            {
                "attributes": {
                    "isPurchasable": true
                }, 
                "countryCode": "DZ"
            }, 
            {
                "attributes": {
                    "isPurchasable": true
                }, 
                "countryCode": "EH"
            }, 
            {
                "attributes": {
                    "isPurchasable": true
                }, 
                "countryCode": "ET"
            }, 
            {
                "attributes": {
                    "isPurchasable": true
                }, 
                "countryCode": "FJ"
            }, 
            {
                "attributes": {
                    "isPurchasable": true
                }, 
                "countryCode": "FM"
            }, 
            {
                "attributes": {
                    "isPurchasable": true
                }, 
                "countryCode": "GA"
            }, 
            {
                "attributes": {
                    "isPurchasable": true
                }, 
                "countryCode": "GB"
            }, 
            {
                "attributes": {
                    "isPurchasable": true
                }, 
                "countryCode": "GH"
            }, 
            {
                "attributes": {
                    "isPurchasable": true
                }, 
                "countryCode": "GM"
            }, 
            {
                "attributes": {
                    "isPurchasable": true
                }, 
                "countryCode": "GN"
            }, 
            {
                "attributes": {
                    "isPurchasable": true
                }, 
                "countryCode": "GQ"
            }, 
            {
                "attributes": {
                    "isPurchasable": true
                }, 
                "countryCode": "GU"
            }, 
            {
                "attributes": {
                    "isPurchasable": true
                }, 
                "countryCode": "GW"
            }, 
            {
                "attributes": {
                    "isPurchasable": true
                }, 
                "countryCode": "HM"
            }, 
            {
                "attributes": {
                    "isPurchasable": true
                }, 
                "countryCode": "KE"
            }, 
            {
                "attributes": {
                    "isPurchasable": true
                }, 
                "countryCode": "KI"
            }, 
            {
                "attributes": {
                    "isPurchasable": true
                }, 
                "countryCode": "KM"
            }, 
            {
                "attributes": {
                    "isPurchasable": true
                }, 
                "countryCode": "LR"
            }, 
            {
                "attributes": {
                    "isPurchasable": true
                }, 
                "countryCode": "LS"
            }, 
            {
                "attributes": {
                    "isPurchasable": true
                }, 
                "countryCode": "MG"
            }, 
            {
                "attributes": {
                    "isPurchasable": true
                }, 
                "countryCode": "MH"
            }, 
            {
                "attributes": {
                    "isPurchasable": true
                }, 
                "countryCode": "ML"
            }, 
            {
                "attributes": {
                    "isPurchasable": true
                }, 
                "countryCode": "MR"
            }, 
            {
                "attributes": {
                    "isPurchasable": true
                }, 
                "countryCode": "MU"
            }, 
            {
                "attributes": {
                    "isPurchasable": true
                }, 
                "countryCode": "MV"
            }, 
            {
                "attributes": {
                    "isPurchasable": true
                }, 
                "countryCode": "MW"
            }, 
            {
                "attributes": {
                    "isPurchasable": true
                }, 
                "countryCode": "MZ"
            }, 
            {
                "attributes": {
                    "isPurchasable": true
                }, 
                "countryCode": "NA"
            }, 
            {
                "attributes": {
                    "isPurchasable": true
                }, 
                "countryCode": "NE"
            }, 
            {
                "attributes": {
                    "isPurchasable": true
                }, 
                "countryCode": "NF"
            }, 
            {
                "attributes": {
                    "isPurchasable": true
                }, 
                "countryCode": "NG"
            }, 
            {
                "attributes": {
                    "isPurchasable": true
                }, 
                "countryCode": "NR"
            }, 
            {
                "attributes": {
                    "isPurchasable": true
                }, 
                "countryCode": "NU"
            }, 
            {
                "attributes": {
                    "isPurchasable": true
                }, 
                "countryCode": "PG"
            }, 
            {
                "attributes": {
                    "isPurchasable": true
                }, 
                "countryCode": "PR"
            }, 
            {
                "attributes": {
                    "isPurchasable": true
                }, 
                "countryCode": "PW"
            }, 
            {
                "attributes": {
                    "isPurchasable": true
                }, 
                "countryCode": "RW"
            }, 
            {
                "attributes": {
                    "isPurchasable": true
                }, 
                "countryCode": "SB"
            }, 
            {
                "attributes": {
                    "isPurchasable": true
                }, 
                "countryCode": "SC"
            }, 
            {
                "attributes": {
                    "isPurchasable": true
                }, 
                "countryCode": "SH"
            }, 
            {
                "attributes": {
                    "isPurchasable": true
                }, 
                "countryCode": "SL"
            }, 
            {
                "attributes": {
                    "isPurchasable": true
                }, 
                "countryCode": "SN"
            }, 
            {
                "attributes": {
                    "isPurchasable": true
                }, 
                "countryCode": "SZ"
            }, 
            {
                "attributes": {
                    "isPurchasable": true
                }, 
                "countryCode": "TD"
            }, 
            {
                "attributes": {
                    "isPurchasable": true
                }, 
                "countryCode": "TG"
            }, 
            {
                "attributes": {
                    "isPurchasable": true
                }, 
                "countryCode": "TK"
            }, 
            {
                "attributes": {
                    "isPurchasable": true
                }, 
                "countryCode": "TN"
            }, 
            {
                "attributes": {
                    "isPurchasable": true
                }, 
                "countryCode": "TV"
            }, 
            {
                "attributes": {
                    "isPurchasable": true
                }, 
                "countryCode": "TZ"
            }, 
            {
                "attributes": {
                    "isPurchasable": true
                }, 
                "countryCode": "UG"
            }, 
            {
                "attributes": {
                    "isPurchasable": true
                }, 
                "countryCode": "US"
            }, 
            {
                "attributes": {
                    "isPurchasable": true
                }, 
                "countryCode": "VI"
            }, 
            {
                "attributes": {
                    "isPurchasable": true
                }, 
                "countryCode": "VU"
            }, 
            {
                "attributes": {
                    "isPurchasable": true
                }, 
                "countryCode": "ZA"
            }, 
            {
                "attributes": {
                    "isPurchasable": true
                }, 
                "countryCode": "ZM"
            }, 
            {
                "attributes": {
                    "isPurchasable": true
                }, 
                "countryCode": "ZW"
            }
        ]
    }, 
    "customAttributes": {
        "gameEditionTypeFacetKeyRankDesc": "3000", 
        "imageServer": "https://Eaassets-a.akamaihd.net/origin-com-store-final-assets-prod"
    }, 
    "defaultLocale": "DEFAULT", 
    "ecommerceAttributes": {
        "addonsAvailable": false, 
        "availableExtraContent": [], 
        "cdnAssetRoot": "http://static.cdn.ea.com/ebisu/u/f/products/1038473"
    }, 
    "financeId": "1038473", 
    "itemId": "Origin.ITM.50.0001142", 
    "localizableAttributes": {
        "backgroundImage": "/195438/1200.0x800.0/1038473_pdpbg_1200x800_en_US_1_^_2016-01-27-14-51-46_73ecb7ccb05fc944e72f8c0324fd38c55f9a2473.jpg", 
        "displayName": "Trine 3: The Artifacts of Power", 
        "longDescription": "Experience a fairytale world of breathtaking sceneries and face a myriad of physics-based puzzles, wonderful contraptions, dangerous foes and enchanting creatures.<br><br>Trine 3: The Artifacts of Power is a platforming game of action, puzzles and adventure, and the sequel to the award winning Trine and Trine 2. Reunite with the familiar heroes - Pontius the Knight, Amadeus the Wizard and Zoya the Thief in an all-new adventure, now for the first time in full 3D!<br><br>Playable in single-player or in co-up with up to three players, both locally or online.<br><br>THE STORY:<br><br>Amadeus the Wizard, Pontius the Knight, and Zoya the Thief have slowly come to the conclusion that having their lives commandeered by a powerful magical artifact is not a desirable state of existence on a permanent basis.<br><br>The heroes try to return their extraordinary gifts to the Artifact called Trine, and so they meddle with powers beyond their understanding: Trine shatters and a heartless ancient sorcerer escapes. With only a broken artifact to guide them, the heroes must try and repair the damage they've caused... or the damage that might yet be done.<br><br><b>THE HEROES:<br><br>AMADEUS</b><br>A married wizard and father of triplets, Amadeus can summon mystical boxes and move obstacles with his spells. Perhaps he is not the most skilled or fearsome of wizards, but the heroes rely on Amadeus on all things concerning magic and legends. Amadeus has always liked adventures more in theory rather than in practice, preferring the fame and tales of his deeds to the actual doing of said deeds, which often deprive him of naps and holidays with his family.<br><br><b>PONTIUS</b><br>The brave protector of the realm with a big heart, Pontius is a champion to anyone in need, regardless of their station. Pontius was knighted by the King himself, and he has a red cape to prove it! He is a frontline hero who is always going headlong first into battle with his trusty shield and sword. In addition to passionately fighting on the side of Goodness and Justice, Pontius has an equal love for good food and drink, and dreams of one day settling down on a simple farm, where he could protect his corner of the world, while growing enormous potatoes and pumpkins. And eat pie.<br><br><b>ZOYA</b><br>Clever and elusive, Zoya gets in and out of tricky situations all the time. She brings her bow and arrows to a fight, but she also has a grappling hook that can be useful in various thiev... situations. Zoya appreciates all the adventures she has had with with Trine, due to all the trinkets she's been able to collect on the way, but she is becoming anxious to get back on her own. Being on call for Trine is nowhere near as thrilling as her old life as a purveyor of rare and precious items.<br><br><b>Trine 3: The Artifacts of Power Features:</b><br><br><b>Online and Local Co-op</b><br>Up to three players can play online and local co-up. Any mix is possible (for example 2 local, 1 online) and you can switch from singleplayer to multiplayer and vice versa. Play with your friends and explore the secrets together!<br><br><b>The Lost Pages</b><br>The ultimate test to your skills, the Lost Pages feature the most incredible contraptions, character-driven design, and ridiculous puzzles. Are you skilled enough to unlock all the Lost Pages?<br><br><b>Soundtrack</b><br>Award-winning composer Ari Pulkkinen returns for an amazing fantasy soundtrack!<br><br><b>Fantastic Fantasy</b><br>Adventure through breathtakingly beautiful landscapes in an enchanting fairytale world, and for the first time ever explore the Trine world in a full 3D setting, allowing you to go check out all the nooks and crannies that have been so alluring in the past.", 
        "packArtLarge": "/195438/231.0x326.0/1038473_LB_231x326_en_US_^_2016-01-27-14-48-06_4fe62c4da43dd8694ea1d33735db050748ce5318.jpg", 
        "packArtMedium": "/195438/142.0x200.0/1038473_MB_142x200_en_US_^_2016-01-27-14-48-27_dcf87500403ec9c42206af3f322ff4ca63ef966b.jpg", 
        "packArtSmall": "/195438/63.0x89.0/1038473_SB_63x89_en_US_^_2016-01-27-14-48-55_a8207fb5bc46c38a840447d2b719df355a918891.jpg", 
        "shortDescription": "Sequel to the award winning Trine and Trine 2."
    }, 
    "mdmHierarchies": {
        "mdmHierarchy": [
            {
                "mdmFranchise": {
                    "franchise": "New IP - Internal Tracking", 
                    "franchiseId": 50318
                }, 
                "mdmMasterTitle": {
                    "masterTitle": "TRINE 3 THE ARTIFACTS OF POWER", 
                    "masterTitleId": 195438
                }, 
                "type": "Primary"
            }
        ]
    }, 
    "offerId": "Origin.OFR.50.0001311", 
    "offerType": "Base Game", 
    "publishing": {
        "publishingAttributes": {
            "contentId": "1038473", 
            "gameDistributionSubType": "Normal Game", 
            "greyMarketControls": false, 
            "isDownloadable": true, 
            "isPublished": true, 
            "originDisplayType": "Full Game"
        }, 
        "softwareControlDates": {
            "softwareControlDate": [
                {
                    "downloadStartDate": "2015-08-20T00:00:00Z", 
                    "platform": "PCWIN", 
                    "releaseDate": "2015-08-20T00:00:00Z"
                }
            ]
        }, 
        "softwareList": {
            "software": [
                {
                    "downloadURLs": {
                        "downloadURL": [
                            {
                                "buildMetaData": "<?xml version=\"1.0\" encoding=\"UTF-8\"?><buildMetaData>\n    <featureFlags allowMultipleInstances=\"0\" autoUpdateEnabled=\"1\" dynamicContentSupportEnabled=\"0\" enableDifferentialUpdate=\"1\" enableOriginInGameAPI=\"0\" forceTouchupInstallerAfterUpdate=\"1\" languageChangeSupportEnabled=\"0\" treatUpdatesAsMandatory=\"0\" useGameVersionFromManifest=\"1\"/>\n    <gameVersion version=\"1.11.0.3103\"/>\n    <requirements clientVersion=\"9.4.5.199\" osMinVersion=\"5.1\" osReqs64Bit=\"false\"/>\n  </buildMetaData>", 
                                "buildReleaseVersion": "1.11.0.3103", 
                                "downloadURL": "/shift/frozenbyte/trine_3:_the_artifacts_of_power/fg_-_ww_x0/trine_3_the_artifacts_of_powerpcfg__ww_x0run_4__20160218_111031035b27bf1ed72e482a9ee985396043008c.zip", 
                                "downloadURLType": "live", 
                                "effectiveDate": "2016-02-19T05:00:00Z"
                            }
                        ]
                    }, 
                    "fulfillmentAttributes": {
                        "achievementSetOverride": "50318_195438_50844", 
                        "cloudSaveConfigurationOverride": "<savefilecriteria> <include order=\"0\">%AppData%/Trine3/</include> </savefilecriteria>", 
                        "downloadPackageType": "DownloadInPlace", 
                        "enableDLCuninstall": false, 
                        "executePathOverride": "[HKEY_LOCAL_MACHINE\\SOFTWARE\\Frozenbyte\\Trine 3 The Artifacts of Power\\Install Dir]trine3_launcher.exe", 
                        "installCheckOverride": "[HKEY_LOCAL_MACHINE\\SOFTWARE\\Frozenbyte\\Trine 3 The Artifacts of Power\\Install Dir]trine3_launcher.exe", 
                        "installationDirectory": "Trine 3 The Artifacts of Power", 
                        "monitorInstall": true, 
                        "monitorPlay": true, 
                        "showKeyDialogOnInstall": false, 
                        "showKeyDialogOnPlay": false
                    }, 
                    "softwareId": "Origin.SFT.50.0000519", 
                    "softwarePlatform": "PCWIN"
                }
            ]
        }, 
        "softwareLocales": {
            "locale": [
                {
                    "value": "da_DK"
                }, 
                {
                    "value": "de_DE"
                }, 
                {
                    "value": "en_US"
                }, 
                {
                    "value": "es_ES"
                }, 
                {
                    "value": "fi_FI"
                }, 
                {
                    "value": "fr_FR"
                }, 
                {
                    "value": "it_IT"
                }, 
                {
                    "value": "ja_JP"
                }, 
                {
                    "value": "no_NO"
                }, 
                {
                    "value": "pt_BR"
                }, 
                {
                    "value": "ru_RU"
                }, 
                {
                    "value": "sv_SE"
                }, 
                {
                    "value": "tr_TR"
                }, 
                {
                    "value": "zh_CN"
                }
            ]
        }
    }, 
    "storeGroupId": "Origin", 
    "updatedDate": "2016-03-31T21:21:03Z"
}