{
    "baseAttributes": {
        "platform": "PCWIN"
    }, 
    "countries": {
        "country": [
            {
                "attributes": {
                    "isPurchasable": true
                }, 
                "countryCode": "AO"
            }, 
            {
                "attributes": {
                    "isPurchasable": true
                }, 
                "countryCode": "BD"
            }, 
            {
                "attributes": {
                    "isPurchasable": true
                }, 
                "countryCode": "BF"
            }, 
            {
                "attributes": {
                    "isPurchasable": true
                }, 
                "countryCode": "BI"
            }, 
            {
                "attributes": {
                    "isPurchasable": true
                }, 
                "countryCode": "BJ"
            }, 
            {
                "attributes": {
                    "isPurchasable": true
                }, 
                "countryCode": "BN"
            }, 
            {
                "attributes": {
                    "isPurchasable": true
                }, 
                "countryCode": "BT"
            }, 
            {
                "attributes": {
                    "isPurchasable": true
                }, 
                "countryCode": "BW"
            }, 
            {
                "attributes": {
                    "isPurchasable": true
                }, 
                "countryCode": "CC"
            }, 
            {
                "attributes": {
                    "isPurchasable": true
                }, 
                "countryCode": "CD"
            }, 
            {
                "attributes": {
                    "isPurchasable": true
                }, 
                "countryCode": "CF"
            }, 
            {
                "attributes": {
                    "isPurchasable": true
                }, 
                "countryCode": "CG"
            }, 
            {
                "attributes": {
                    "isPurchasable": true
                }, 
                "countryCode": "CI"
            }, 
            {
                "attributes": {
                    "isPurchasable": true
                }, 
                "countryCode": "CM"
            }, 
            {
                "attributes": {
                    "isPurchasable": true
                }, 
                "countryCode": "CV"
            }, 
            {
                "attributes": {
                    "isPurchasable": false
                }, 
                "countryCode": "DEFAULT"
            }, 
            {
                "attributes": {
                    "isPurchasable": true
                }, 
                "countryCode": "DJ"
            }, 
            {
                "attributes": {
                    "isPurchasable": true
                }, 
                "countryCode": "DZ"
            }, 
            {
                "attributes": {
                    "isPurchasable": true
                }, 
                "countryCode": "EH"
            }, 
            {
                "attributes": {
                    "isPurchasable": true
                }, 
                "countryCode": "ET"
            }, 
            {
                "attributes": {
                    "isPurchasable": true
                }, 
                "countryCode": "GA"
            }, 
            {
                "attributes": {
                    "isPurchasable": true
                }, 
                "countryCode": "GH"
            }, 
            {
                "attributes": {
                    "isPurchasable": true
                }, 
                "countryCode": "GM"
            }, 
            {
                "attributes": {
                    "isPurchasable": true
                }, 
                "countryCode": "GN"
            }, 
            {
                "attributes": {
                    "isPurchasable": true
                }, 
                "countryCode": "GQ"
            }, 
            {
                "attributes": {
                    "isPurchasable": true
                }, 
                "countryCode": "GW"
            }, 
            {
                "attributes": {
                    "isPurchasable": true
                }, 
                "countryCode": "HK"
            }, 
            {
                "attributes": {
                    "isPurchasable": true
                }, 
                "countryCode": "ID"
            }, 
            {
                "attributes": {
                    "isPurchasable": true
                }, 
                "countryCode": "IN"
            }, 
            {
                "attributes": {
                    "isPurchasable": true
                }, 
                "countryCode": "KE"
            }, 
            {
                "attributes": {
                    "isPurchasable": true
                }, 
                "countryCode": "KH"
            }, 
            {
                "attributes": {
                    "isPurchasable": true
                }, 
                "countryCode": "KM"
            }, 
            {
                "attributes": {
                    "isPurchasable": true
                }, 
                "countryCode": "KR"
            }, 
            {
                "attributes": {
                    "isPurchasable": true
                }, 
                "countryCode": "LA"
            }, 
            {
                "attributes": {
                    "isPurchasable": true
                }, 
                "countryCode": "LK"
            }, 
            {
                "attributes": {
                    "isPurchasable": true
                }, 
                "countryCode": "LR"
            }, 
            {
                "attributes": {
                    "isPurchasable": true
                }, 
                "countryCode": "LS"
            }, 
            {
                "attributes": {
                    "isPurchasable": true
                }, 
                "countryCode": "MG"
            }, 
            {
                "attributes": {
                    "isPurchasable": true
                }, 
                "countryCode": "ML"
            }, 
            {
                "attributes": {
                    "isPurchasable": true
                }, 
                "countryCode": "MM"
            }, 
            {
                "attributes": {
                    "isPurchasable": true
                }, 
                "countryCode": "MO"
            }, 
            {
                "attributes": {
                    "isPurchasable": true
                }, 
                "countryCode": "MP"
            }, 
            {
                "attributes": {
                    "isPurchasable": true
                }, 
                "countryCode": "MR"
            }, 
            {
                "attributes": {
                    "isPurchasable": true
                }, 
                "countryCode": "MU"
            }, 
            {
                "attributes": {
                    "isPurchasable": true
                }, 
                "countryCode": "MV"
            }, 
            {
                "attributes": {
                    "isPurchasable": true
                }, 
                "countryCode": "MW"
            }, 
            {
                "attributes": {
                    "isPurchasable": true
                }, 
                "countryCode": "MY"
            }, 
            {
                "attributes": {
                    "isPurchasable": true
                }, 
                "countryCode": "MZ"
            }, 
            {
                "attributes": {
                    "isPurchasable": true
                }, 
                "countryCode": "NA"
            }, 
            {
                "attributes": {
                    "isPurchasable": true
                }, 
                "countryCode": "NE"
            }, 
            {
                "attributes": {
                    "isPurchasable": true
                }, 
                "countryCode": "NG"
            }, 
            {
                "attributes": {
                    "isPurchasable": true
                }, 
                "countryCode": "NP"
            }, 
            {
                "attributes": {
                    "isPurchasable": true
                }, 
                "countryCode": "PH"
            }, 
            {
                "attributes": {
                    "isPurchasable": true
                }, 
                "countryCode": "PK"
            }, 
            {
                "attributes": {
                    "isPurchasable": true
                }, 
                "countryCode": "RW"
            }, 
            {
                "attributes": {
                    "isPurchasable": true
                }, 
                "countryCode": "SC"
            }, 
            {
                "attributes": {
                    "isPurchasable": true
                }, 
                "countryCode": "SG"
            }, 
            {
                "attributes": {
                    "isPurchasable": true
                }, 
                "countryCode": "SH"
            }, 
            {
                "attributes": {
                    "isPurchasable": true
                }, 
                "countryCode": "SL"
            }, 
            {
                "attributes": {
                    "isPurchasable": true
                }, 
                "countryCode": "SN"
            }, 
            {
                "attributes": {
                    "isPurchasable": true
                }, 
                "countryCode": "SZ"
            }, 
            {
                "attributes": {
                    "isPurchasable": true
                }, 
                "countryCode": "TD"
            }, 
            {
                "attributes": {
                    "isPurchasable": true
                }, 
                "countryCode": "TG"
            }, 
            {
                "attributes": {
                    "isPurchasable": true
                }, 
                "countryCode": "TH"
            }, 
            {
                "attributes": {
                    "isPurchasable": true
                }, 
                "countryCode": "TL"
            }, 
            {
                "attributes": {
                    "isPurchasable": true
                }, 
                "countryCode": "TN"
            }, 
            {
                "attributes": {
                    "isPurchasable": true
                }, 
                "countryCode": "TW"
            }, 
            {
                "attributes": {
                    "isPurchasable": true
                }, 
                "countryCode": "TZ"
            }, 
            {
                "attributes": {
                    "isPurchasable": true
                }, 
                "countryCode": "UG"
            }, 
            {
                "attributes": {
                    "isPurchasable": true
                }, 
                "countryCode": "VN"
            }, 
            {
                "attributes": {
                    "isPurchasable": true
                }, 
                "countryCode": "ZA"
            }, 
            {
                "attributes": {
                    "isPurchasable": true
                }, 
                "countryCode": "ZM"
            }, 
            {
                "attributes": {
                    "isPurchasable": true
                }, 
                "countryCode": "ZW"
            }
        ]
    }, 
    "customAttributes": {
        "gameEditionTypeFacetKeyRankDesc": "3000", 
        "imageServer": "https://Eaassets-a.akamaihd.net/origin-com-store-final-assets-prod"
    }, 
    "defaultLocale": "DEFAULT", 
    "ecommerceAttributes": {
        "addonsAvailable": false, 
        "availableExtraContent": [], 
        "cdnAssetRoot": "http://static.cdn.ea.com/ebisu/u/f/products/1064667"
    }, 
    "financeId": "1064667", 
    "itemId": "Origin.ITM.50.0002142", 
    "itemName": "A Way Out - PC - ROA (Origin)", 
    "localizableAttributes": {
        "displayName": "A Way Out - ROA (Friend Pass)", 
        "longDescription": "From the creators of Brothers \u2013 A Tale of Two Sons comes A Way Out, an exclusively co-op adventure where you play the role of one of two prisoners making their daring escape from prison.\n<br><br>\nWhat begins as a thrilling breakout quickly turns into an unpredictable, emotional adventure unlike anything seen or played before. \n<br><br>\nA Way Out is an experience that must be played with two players. Each player controls one of the main characters, Leo and Vincent, in a reluctant alliance to break out of prison and gain their freedom.\n<br><br>\nPlay the entire experience with your friends for free using the friends pass free trial feature. When you purchase the full game, you can invite any of your friends online regardless of whether or not they\u2019ve purchased the game.  From the in-game menu, send them an invite, they\u2019ll unlock the Free Trial, and then you\u2019re ready to play the entire experience together.", 
        "packArtLarge": "/196487/231.0x326.0/1064664_LB_231x326_en_US_^_2018-03-19-15-55-47_acbdd79abe3bad20e143480d3267d7b30fbb3d91.jpg", 
        "packArtMedium": "/196487/142.0x200.0/1064664_MB_142x200_en_US_^_2018-03-19-15-55-47_7be2e7649df7da3a6178e02139d5fd904c9a8523.jpg", 
        "packArtSmall": "/196487/63.0x89.0/1064664_SB_63x89_en_US_^_2018-03-19-15-55-47_da58fe79f6782a9e7f2df218a876ac43c1dbdd12.jpg", 
        "shortDescription": "A Way Out - ROA (Friend Pass)"
    }, 
    "mdmHierarchies": {
        "mdmHierarchy": [
            {
                "mdmFranchise": {
                    "franchise": "New IP - Internal Tracking", 
                    "franchiseId": 50318
                }, 
                "mdmMasterTitle": {
                    "masterTitle": "A WAY OUT", 
                    "masterTitleId": 196487
                }, 
                "type": "Primary"
            }
        ]
    }, 
    "offerId": "Origin.OFR.50.0002495", 
    "offerType": "Base Game", 
    "publishing": {
        "publishingAttributes": {
            "contentId": "1028663_oa", 
            "gameDistributionSubType": "Gameplay Timer Trial - Game Time", 
            "greyMarketControls": true, 
            "isDownloadable": true, 
            "isPublished": false, 
            "originDisplayType": "Full Game", 
            "trialLaunchDuration": 10000
        }, 
        "softwareControlDates": {
            "softwareControlDate": [
                {
                    "downloadStartDate": "2018-03-22T13:00:00Z", 
                    "platform": "PCWIN", 
                    "releaseDate": "2018-03-22T13:00:00Z"
                }
            ]
        }, 
        "softwareList": {
            "software": [
                {
                    "downloadURLs": {
                        "downloadURL": [
                            {
                                "buildMetaData": "<?xml version=\"1.0\" encoding=\"UTF-8\"?><buildMetaData>\n    <featureFlags allowMultipleInstances=\"0\" autoUpdateEnabled=\"1\" dynamicContentSupportEnabled=\"1\" enableDifferentialUpdate=\"1\" enableOriginInGameAPI=\"0\" forceTouchupInstallerAfterUpdate=\"1\" languageChangeSupportEnabled=\"1\" treatUpdatesAsMandatory=\"1\" useGameVersionFromManifest=\"1\"/>\n    <gameVersion version=\"1.0.62.0\"/>\n    <requirements osMinVersion=\"6.1\" osReqs64Bit=\"True\"/>\n  </buildMetaData>", 
                                "buildReleaseVersion": "1.0.62.0", 
                                "downloadURL": "/shift/hazelight/a_way_out/fg__ww/a_way_outpcfg__wwalpha_3__10621025830d2023a6753a4b18bc0ef5aa1e872573.zip", 
                                "downloadURLType": "live", 
                                "effectiveDate": "2018-03-09T18:00:00Z"
                            }
                        ]
                    }, 
                    "fulfillmentAttributes": {
                        "achievementSetOverride": "50318_194125_50844", 
                        "cloudSaveConfigurationOverride": "<saveFileCriteria>\n<exclude order=\"0\">%Documents%/My Games/A Way Out/LocalSettings</exclude>\n<include order=\"1\">%Documents%/My Games/A Way Out/GameSettings</include>\n<include order=\"2\">%Documents%/My Games/A Way Out/AWO-Progression</include>\n<include order=\"3\">%Documents%/My Games/A Way Out/Saves/</include>\n</saveFileCriteria>", 
                        "downloadPackageType": "DownloadInPlace", 
                        "enableDLCuninstall": false, 
                        "executePathOverride": "[HKEY_LOCAL_MACHINE\\SOFTWARE\\Hazelight\\AWayOut\\Install Dir]\\Haze1\\Binaries\\Win64\\AWayOut.exe", 
                        "installCheckOverride": "[HKEY_LOCAL_MACHINE\\SOFTWARE\\Hazelight\\AWayOut\\Install Dir]\\Haze1\\Binaries\\Win64\\AWayOut.exe", 
                        "installationDirectory": "AWayOut", 
                        "monitorInstall": true, 
                        "monitorPlay": true, 
                        "multiPlayerId": "1028663", 
                        "processorArchitecture": "64-bit", 
                        "showKeyDialogOnInstall": false, 
                        "showKeyDialogOnPlay": false
                    }, 
                    "softwareId": "Origin.SFT.50.0000658", 
                    "softwarePlatform": "PCWIN"
                }
            ]
        }, 
        "softwareLocales": {
            "locale": [
                {
                    "value": "en_US"
                }
            ]
        }
    }, 
    "storeGroupId": "Origin", 
    "updatedDate": "2018-03-22T18:56:01Z"
}